schwab_api_py/__init__.py
schwab_api_py/api.py
schwab_api_lq-0.0.2.dist-info/LICENSE
schwab_api_lq-0.0.2.dist-info/METADATA
schwab_api_lq-0.0.2.dist-info/WHEEL
schwab_api_lq-0.0.2.dist-info/top_level.txt
schwab_api_lq-0.0.2.dist-info/RECORD
