Metadata-Version: 2.1
Name: schwab_api_lq
Version: 0.0.2
Summary: Unofficial Schwab API wrapper in Python 3.
Home-page: https://github.com/lqepoch/schwab-api-lq
Download-URL: https://github.com/lqepoch/schwab-api-lq/tarball/main
Author: LQEPOCH
Author-email: lqepoch@gmail.com
License: MIT
Keywords: schwab,python3,api,unofficial,schwab-api,schwab charles api
Classifier: Development Status :: 3 - Alpha
Classifier: Intended Audience :: Developers
Classifier: Topic :: Software Development :: Build Tools
Classifier: License :: OSI Approved :: MIT License
Classifier: Programming Language :: Python :: 3.7
Classifier: Programming Language :: Python :: 3.8
Classifier: Programming Language :: Python :: 3.9
Classifier: Programming Language :: Python :: 3.10
Classifier: Programming Language :: Python :: 3.11
Classifier: Programming Language :: Python :: 3.12
Requires-Python: >=3.6
License-File: LICENSE
Requires-Dist: playwright
Requires-Dist: playwright-stealth
Requires-Dist: pyotp
Requires-Dist: python-vipaccess
